easyinput/__init__.py
easyinput/tokenizer.py
easyinput/utils.py
easyinput-2.4.dist-info/LICENSE.txt
easyinput-2.4.dist-info/METADATA
easyinput-2.4.dist-info/WHEEL
easyinput-2.4.dist-info/top_level.txt
easyinput-2.4.dist-info/RECORD
